__init__.py
conftest.py
ppxgboost/OPEMetadata.py
ppxgboost/PPKey.py
ppxgboost/PPModel.py
ppxgboost/PPPrediction.py
ppxgboost/PPQuery.py
ppxgboost/PPTree.py
ppxgboost/PaillierAPI.py
ppxgboost/__init__.py
ppxgboost-0.0.2.dist-info/licenses/LICENSE
ppxgboost-0.0.2.dist-info/licenses/NOTICE
ppxgboost-0.0.2.dist-info/METADATA
ppxgboost-0.0.2.dist-info/WHEEL
ppxgboost-0.0.2.dist-info/top_level.txt
ppxgboost-0.0.2.dist-info/RECORD
